{"id":"mil-sentimientos","name":"Mil Sentimientos","artists":[{"id":"frankalvarez","name":"Frank Alvarez","url":"https://xpendmusic.com/artistas/frankalvarez/","key":"/artistas/frankalvarez"}],"type":"album","url":"https://xpend.fanlink.to/cZWn","services":[{"name":"spotify","url":"https://open.spotify.com/album/1FUKj86ejJVNEHrVIPsPO8"},{"name":"apple","url":"https://music.apple.com/album/mil-sentimientos/1507143738"},{"name":"youtube","url":"https://www.youtube.com/playlist?list=PL9t9lHRgi2DbFjT_2tShKKLJeubh0M_c4"}],"img":"mil-sentimientos.jpg","date":"06-04-2020","image":"https://cdn-v2.xpendmusic.com/media/mil-sentimientos.jpg"}